nemosyne/S3.py
nemosyne/__init__.py
nemosyne/config.py
nemosyne/main.py
nemosyne/uploader.py
nemosyne-0.0.1.dist-info/entry_points.txt
nemosyne-0.0.1.dist-info/LICENSE
nemosyne-0.0.1.dist-info/WHEEL
nemosyne-0.0.1.dist-info/METADATA
nemosyne-0.0.1.dist-info/RECORD
