Metadata-Version: 2.1
Name: nemosyne
Version: 0.0.1
Summary: nemosyne (aka [Mnemosyne](https://en.wikipedia.org/wiki/Mnemosyne)) is an S3 command-line manager.WIP
Author: Ali Tavallaie
Author-email: a.tavallaie@gmail.com
Requires-Python: >=3.8,<4.0
Classifier: Programming Language :: Python :: 3
Classifier: Programming Language :: Python :: 3.8
Classifier: Programming Language :: Python :: 3.9
Requires-Dist: CacheControl (==0.12.6)
Requires-Dist: appdirs (==1.4.3)
Requires-Dist: boto3 (==1.17.96)
Requires-Dist: botocore (==1.20.96)
Requires-Dist: certifi (==2019.11.28)
Requires-Dist: chardet (==3.0.4)
Requires-Dist: click (==7.1.2)
Requires-Dist: colorama (==0.4.3)
Requires-Dist: contextlib2 (==0.6.0)
Requires-Dist: distlib (==0.3.0)
Requires-Dist: distro (==1.4.0)
Requires-Dist: html5lib (==1.0.1)
Requires-Dist: idna (==2.8)
Requires-Dist: ipaddr (==2.2.0)
Requires-Dist: jmespath (==0.10.0)
Requires-Dist: lockfile (==0.12.2)
Requires-Dist: msgpack (==0.6.2)
Requires-Dist: packaging (==20.3)
Requires-Dist: pep517 (==0.8.2)
Requires-Dist: progress (==1.5)
Requires-Dist: pyparsing (==2.4.6)
Requires-Dist: python-dateutil (==2.8.1)
Requires-Dist: python-dotenv (==0.17.1)
Requires-Dist: pytoml (==0.1.21)
Requires-Dist: requests (==2.22.0)
Requires-Dist: retrying (==1.3.3)
Requires-Dist: s3transfer (==0.4.2)
Requires-Dist: six (==1.14.0)
Requires-Dist: typer (==0.3.2)
Requires-Dist: urllib3 (==1.25.8)
Requires-Dist: webencodings (==0.5.1)
